MANIFEST.in
README
clean.sh
requirements.txt
setup.py
atmosphere_python_client.egg-info/PKG-INFO
atmosphere_python_client.egg-info/SOURCES.txt
atmosphere_python_client.egg-info/dependency_links.txt
atmosphere_python_client.egg-info/pbr.json
atmosphere_python_client.egg-info/requires.txt
atmosphere_python_client.egg-info/top_level.txt
src/atmosphere/__init__.py
src/atmosphere/config.py
src/atmosphere/tools.py
src/atmosphere/appliance/__init__.py
src/atmosphere/appliance/appliance_configuration_templates.py
src/atmosphere/appliance/appliance_sets.py
src/atmosphere/appliance/appliance_types.py
src/atmosphere/appliance/appliances.py
src/atmosphere/machine/__init__.py
src/atmosphere/machine/compute_sites.py
src/atmosphere/machine/virtual_machines.py
src/atmosphere/machine/virtual_machines_templates.py
src/atmosphere/mapping/__init__.py
src/atmosphere/mapping/endpoint.py
src/atmosphere/mapping/http_mappings.py
src/atmosphere/mapping/port_mapping_templates.py
src/atmosphere/mapping/port_mappings.py
src/atmosphere/property/__init__.py
src/atmosphere/property/dev_mode_property_sets.py