Metadata-Version: 1.1
Name: atmosphere-python-client
Version: 1.0
Summary: Atmosphere REST API client written in python
Home-page: https://github.com/dice-cyfronet/atmosphere-python-client
Author: Paweł Suder
Author-email: pawel@suder.info
License: UNKNOWN
Download-URL: https://github.com/dice-cyfronet/atmosphere-python-client/archive/master.zip
Keywords: atmosphere
Platform: UNKNOWN
Classifier: Programming Language :: Python
Classifier: Development Status :: 4 - Beta
Classifier: Environment :: Other Environment
Classifier: Intended Audience :: Developers
Classifier: License :: Other/Proprietary License
Classifier: Operating System :: OS Independent
